multistop/__init__.py
multistop/code.py
multistop/stopwords.pkl
multistop-1.3.dist-info/METADATA
multistop-1.3.dist-info/WHEEL
multistop-1.3.dist-info/top_level.txt
multistop-1.3.dist-info/RECORD
