Metadata-Version: 2.1
Name: multistop
Version: 1.3
Summary: 文本分析停用词表，支持中英德法等15种语言。
Home-page: https://github.com/hidadeng/cnstopwords
Author: 大邓
Author-email: thunderhit@qq.com
License: MIT
Keywords: chinese text analysis,text analysis,text mining,stopwords,natural language processing
Platform: UNKNOWN
Requires-Python: >=3.5
Requires-Dist: jieba
Requires-Dist: numpy
